__init__.py
yxd.py
yxdconfig.py
yxdump-1.0.1.dist-info/METADATA
yxdump-1.0.1.dist-info/WHEEL
yxdump-1.0.1.dist-info/entry_points.txt
yxdump-1.0.1.dist-info/licenses/LICENSE
yxdump-1.0.1.dist-info/RECORD
