Metadata-Version: 2.1
Name: yxdump
Version: 1.0.1
Summary: Yuu's heX Dumper
Project-URL: Homepage, https://github.com/netspooky/yxd
Project-URL: Bug Tracker, https://github.com/netspooky/yxd/issues
Author-email: netspooky <u+yxd@n0.lol>
License-File: LICENSE
Classifier: License :: OSI Approved :: MIT License
Classifier: Operating System :: OS Independent
Classifier: Programming Language :: Python :: 3
Requires-Python: >=3.7
